adder.t.v
//For each device, first write a test bench that verifies the appropriate behavior of your device. We have already completed this for you for the 2 bit decoder as an //example, so you will only have to write the other two.

//The test bench should:

//Instantiate a copy of the device it is testing (Device Under Test = DUT)
//Show what the truth table should be
//Show what the truth table is

// Adder testbench
`timescale 1 ns / 1 ps
`include "adder.v"

module testFullAdder();
    //reg a, b, carryin;
    reg[3:0] a, b;
    //wire sum, carryout;
    wire[3:0] sum;
    wire carryout, overflow;

    //behavioralFullAdder adder(sum, carryout, a, b, carryin);
    //structuralFullAdder adder (sum, carryout, a, b, carryin);
    FullAdder4bit adder(sum, carryout, overflow, a, b);

    initial begin
    $dumpfile("adder.vcd"); //for gtkwave
    $dumpvars;

    $display("A      B    | Cout  Sum  Overflow | Expected Output");
    $display("Positive + Positive, no overflow");
    a=4'b0000;b=4'b0001; #1000
    $display("%b  %b  |  %b    %b   %b      |    0, 0001, 0    ", a, b, carryout, sum, overflow);

    a=4'b0100;b=4'b0010; #1000
    $display("%b  %b  |  %b    %b   %b      |    0, 0110, 0    ", a, b, carryout, sum, overflow);

    a=4'b0101;b=4'b0001; #1000
    $display("%b  %b  |  %b    %b   %b      |    0, 0110, 0    ", a, b, carryout, sum, overflow);

    a=4'b0010;b=4'b0011; #1000
    $display("%b  %b  |  %b    %b   %b      |    0, 0101, 0    ", a, b, carryout, sum, overflow);

    $display("Negative + Negative, no overflow");
    a=4'b1110;b=4'b1100; #1000
    $display("%b  %b  |  %b    %b   %b      |    1, 1010, 0    ", a, b, carryout, sum, overflow);

    a=4'b1001;b=4'b1111; #1000
    $display("%b  %b  |  %b    %b   %b      |    1, 1000, 0    ", a, b, carryout, sum, overflow);

    a=4'b1101;b=4'b1100; #1000
    $display("%b  %b  |  %b    %b   %b      |    1, 1001, 0    ", a, b, carryout, sum, overflow);

    a=4'b1100;b=4'b1111; #1000
    $display("%b  %b  |  %b    %b   %b      |    1, 1011, 0    ", a, b, carryout, sum, overflow);

    $display("Positive + Negative, no overflow");
    a=4'b0011;b=4'b1100; #1000
    $display("%b  %b  |  %b    %b   %b      |    0, 1111, 0    ", a, b, carryout, sum, overflow);

    a=4'b0111;b=4'b1110; #1000
    $display("%b  %b  |  %b    %b   %b      |    1, 0101, 0    ", a, b, carryout, sum, overflow);

    a=4'b1010;b=4'b0001; #1000
    $display("%b  %b  |  %b    %b   %b      |    0, 1011, 0    ", a, b, carryout, sum, overflow);

    a=4'b0101;b=4'b1000; #1000
    $display("%b  %b  |  %b    %b   %b      |    0, 1101, 0    ", a, b, carryout, sum, overflow);

    $display("Overflow");
    a=4'b0111;b=4'b0110; #1000
    $display("%b  %b  |  %b    %b   %b      |    0, 1101, 1    ", a, b, carryout, sum, overflow);

    a=4'b0101;b=4'b0100; #1000
    $display("%b  %b  |  %b    %b   %b      |    0, 1001, 1    ", a, b, carryout, sum, overflow);

    a=4'b1001;b=4'b1010; #1000
    $display("%b  %b  |  %b    %b   %b      |    1, 0011, 1    ", a, b, carryout, sum, overflow);

    a=4'b1101;b=4'b1000; #1000
    $display("%b  %b  |  %b    %b   %b      |    1, 0101, 1    ", a, b, carryout, sum, overflow);

    end

endmodule

adder.v
// Adder circuit
`define AND and #50
`define OR or #50
`define NOT not #50
`define XOR xor #50

module behavioralFullAdder
(
    output sum,
    output carryout,
    input a,
    input b,
    input carryin
);
    // Uses concatenation operator and built-in '+'
    assign {carryout, sum}=a+b+carryin;
endmodule

module structuralFullAdder
(
    output sum,
    output carryout,
    input a,
    input b,
    input carryin
);
    // Your adder code here
    wire AxorB;
    wire AandB;
    wire AxorBandCin;

    `XOR xorgate1(AxorB, a, b);
    `XOR xorgate2(sum, AxorB, carryin);

    `AND andgate1(AandB, a, b);
    `AND andgate2(AxorBandCin, AxorB, carryin);
    `OR orgate(carryout, AandB, AxorBandCin);

    

endmodule

module FullAdder4bit
(
    output[3:0] sum,  // 2's complement sum of a and b
    output carryout,  // Carry out of the summation of a and b
    output overflow,  // True if the calculation resulted in an overflow
    input[3:0] a,     // First operand in 2's complement format
    input[3:0] b      // Second operand in 2's complement format
);

    

    wire carryout0;
    wire carryout1;
    wire carryout2;
    

    structuralFullAdder adder0(sum[0], carryout0, a[0], b[0], 0); // carryin=0 for first bit
    //and andgate0(tempCarryout, carryout, 1);
    structuralFullAdder adder1(sum[1], carryout1, a[1], b[1], carryout0); // carryin=0 for first bit
    structuralFullAdder adder2(sum[2], carryout2, a[2], b[2], carryout1); // carryin=0 for first bit
    structuralFullAdder adder3(sum[3], carryout, a[3], b[3], carryout2); // carryin=0 for first bit

    // figure out if overflow
    wire nA3;
    wire nB3;
    wire nS3;
    wire andtop;
    wire andbottom;

    `NOT notgatea(nA3, a[3]);
    `NOT notgateb(nB3, b[3]);
    `NOT notgates(nS3, sum[3]);

    `AND andgate1(andtop, nA3, nB3, sum[3]);
    `AND andgate2(andbottom, a[3], b[3], nS3);

    `OR orgate(overflow, andtop, andbottom);

endmodule

adder.vcd
$date
	Sun Sep 25 18:01:41 2016
$end
$version
	Icarus Verilog
$end
$timescale
	1ps
$end
$scope module behavioralFullAdder $end
$var wire 1 ! a $end
$var wire 1 " b $end
$var wire 1 # carryin $end
$var wire 1 $ carryout $end
$var wire 1 % sum $end
$upscope $end
$scope module testFullAdder $end
$var wire 1 & carryout $end
$var wire 1 ' overflow $end
$var wire 4 ( sum [3:0] $end
$var reg 4 ) a [3:0] $end
$var reg 4 * b [3:0] $end
$scope module adder $end
$var wire 4 + a [3:0] $end
$var wire 1 , andbottom $end
$var wire 1 - andtop $end
$var wire 4 . b [3:0] $end
$var wire 1 & carryout $end
$var wire 1 / carryout0 $end
$var wire 1 0 carryout1 $end
$var wire 1 1 carryout2 $end
$var wire 1 2 nA3 $end
$var wire 1 3 nB3 $end
$var wire 1 4 nS3 $end
$var wire 1 ' overflow $end
$var wire 4 5 sum [3:0] $end
$scope module adder0 $end
$var wire 1 6 AandB $end
$var wire 1 7 AxorB $end
$var wire 1 8 AxorBandCin $end
$var wire 1 9 a $end
$var wire 1 : b $end
$var wire 1 ; carryin $end
$var wire 1 / carryout $end
$var wire 1 < sum $end
$upscope $end
$scope module adder1 $end
$var wire 1 = AandB $end
$var wire 1 > AxorB $end
$var wire 1 ? AxorBandCin $end
$var wire 1 @ a $end
$var wire 1 A b $end
$var wire 1 / carryin $end
$var wire 1 0 carryout $end
$var wire 1 B sum $end
$upscope $end
$scope module adder2 $end
$var wire 1 C AandB $end
$var wire 1 D AxorB $end
$var wire 1 E AxorBandCin $end
$var wire 1 F a $end
$var wire 1 G b $end
$var wire 1 0 carryin $end
$var wire 1 1 carryout $end
$var wire 1 H sum $end
$upscope $end
$scope module adder3 $end
$var wire 1 I AandB $end
$var wire 1 J AxorB $end
$var wire 1 K AxorBandCin $end
$var wire 1 L a $end
$var wire 1 M b $end
$var wire 1 1 carryin $end
$var wire 1 & carryout $end
$var wire 1 N sum $end
$upscope $end
$upscope $end
$upscope $end
$enddefinitions $end
#0
$dumpvars
xN
0M
0L
xK
zJ
zI
xH
0G
0F
xE
zD
zC
xB
0A
0@
x?
z>
z=
x<
0;
1:
09
z8
z7
z6
bx 5
x4
z3
z2
x1
x0
x/
b1 .
x-
z,
b0 +
b1 *
b0 )
bx (
x'
x&
x%
x$
z#
z"
z!
$end
#50000
12
13
0I
0J
0C
0D
0=
0>
08
06
17
0,
#100000
0K
0E
0?
0/
1<
bx1 (
bx1 5
#150000
0&
01
00
0B
bx01 (
bx01 5
#200000
0N
0H
b1 (
b1 5
#250000
14
0-
#300000
0'
#1000000
0:
1A
1F
b10 *
b10 .
b100 )
b100 +
#1050000
07
1>
1D
#1100000
0<
1B
1H
b110 (
b110 5
#2000000
1:
0A
19
b1 *
b1 .
b101 )
b101 +
#2050000
0>
16
#2100000
0B
b100 (
b100 5
1/
#2150000
1B
b110 (
b110 5
#3000000
1A
09
1@
0F
b11 *
b11 .
b10 )
b10 +
#3050000
17
06
1=
0D
#3100000
1<
0/
10
0H
b11 (
b11 5
#3150000
0B
1H
b101 (
b101 5
#4000000
0:
0A
1G
1M
1F
1L
b1100 *
b1100 .
b1110 )
b1110 +
#4050000
07
1>
0=
03
1C
1I
02
1,
#4100000
0<
1B
b110 (
b110 5
00
11
1&
1'
#4150000
0H
1N
b1010 (
b1010 5
#4200000
04
#4250000
0,
#4300000
0'
#5000000
1:
1A
19
0@
0F
b1111 *
b1111 .
b1001 )
b1001 +
#5050000
16
1D
0C
#5100000
1/
1H
b1110 (
b1110 5
01
#5150000
0B
1?
0N
b100 (
b100 5
#5200000
14
10
#5250000
1,
0H
b0 (
b0 5
1E
#5300000
1'
11
#5350000
1N
b1000 (
b1000 5
#5400000
04
#5450000
0,
#5500000
0'
#6000000
0:
0A
1F
b1100 *
b1100 .
b1101 )
b1101 +
#6050000
17
06
0>
0D
1C
#6100000
1<
0/
1B
0?
1H
b1111 (
b1111 5
0E
#6150000
0B
b1101 (
b1101 5
00
#6200000
0H
b1001 (
b1001 5
#7000000
1:
1A
09
b1111 *
b1111 .
b1100 )
b1100 +
#7050000
1>
#7100000
1B
b1011 (
b1011 5
#8000000
0:
0A
19
1@
0F
0L
b1100 *
b1100 .
b11 )
b11 +
#8050000
1D
0C
1J
0I
12
#8100000
1H
01
0N
b111 (
b111 5
1K
0&
#8150000
14
1N
b1111 (
b1111 5
0K
1&
#8200000
04
0&
#9000000
1A
1F
b1110 *
b1110 .
b111 )
b111 +
#9050000
0>
1=
0D
1C
#9100000
0B
10
0H
b1001 (
b1001 5
11
#9150000
1H
0N
b101 (
b101 5
1K
#9200000
14
1&
#10000000
1:
0A
0G
0M
09
0F
1L
b1 *
b1 .
b1010 )
b1010 +
#10050000
1>
0=
13
0C
02
#10100000
1B
b111 (
b111 5
00
01
#10150000
0H
1N
b1011 (
b1011 5
0K
#10200000
04
0&
#11000000
0:
1M
19
0@
1F
0L
b1000 *
b1000 .
b101 )
b101 +
#11050000
03
0>
1D
12
#11100000
0B
1H
b1101 (
b1101 5
#12000000
1A
1G
0M
1@
b110 *
b110 .
b111 )
b111 +
#12050000
0D
1C
0J
13
1=
#12100000
0H
11
0N
b1 (
b1 5
1-
10
#12150000
14
0-
1N
1'
1H
b1101 (
b1101 5
#12200000
04
1-
0'
#12250000
1'
#13000000
0A
0@
b100 *
b100 .
b101 )
b101 +
#13050000
0=
#13100000
00
#13150000
0H
b1001 (
b1001 5
#14000000
1A
0G
1M
0F
1L
b1010 *
b1010 .
b1001 )
b1001 +
#14050000
1>
03
0C
1I
02
#14100000
1B
b1011 (
b1011 5
01
1&
0-
#14150000
0N
b11 (
b11 5
0'
#14200000
14
#14250000
1,
#14300000
1'
#15000000
0A
1F
b1000 *
b1000 .
b1101 )
b1101 +
#15050000
0>
1D
#15100000
0B
1H
b101 (
b101 5
