adder.v
`define AND and #50
`define OR or #50
`define NOT not #50
`define XOR xor #50

module FullAdder1bit
(
    output sum, 
    output carryout,
    input a, 
    input b, 
    input carryin
);
    wire axorb;
    wire aandb;
    wire axorb_and_c;
    `XOR xorgate1(axorb,a,b);
    `AND andgate1(aandb,a,b);
    `AND andgate2(axorb_and_c,carryin,axorb);
    `XOR xorgate2(sum,carryin,axorb);
    `OR orgate(carryout,axorb_and_c,aandb);
endmodule

 module FullAdder4bit
(
    output[3:0] sum,  // 2's complement sum of a and b
    output carryout,  // Carry out of the summation of a and b
    output overflow,  // True if the calculation resulted in an overflow
    input[3:0] a,     // First operand in 2's complement format
    input[3:0] b      // Second operand in 2's complement format
);

wire carryin = 0;

wire carryout_0;
wire carryout_1; 
wire carryout_2;

FullAdder1bit fa1(sum[0],carryout_0,a[0],b[0],carryin);
FullAdder1bit fa2(sum[1],carryout_1,a[1],b[1],carryout_0);
FullAdder1bit fa3(sum[2],carryout_2,a[2],b[2],carryout_1);
FullAdder1bit fa4(sum[3],carryout,a[3],b[3],carryout_2);
`XOR xorgate(overflow, carryout, carryout_2);
//`AND andgate(overflow, carryout, 1);
//overflow = carryout;

endmodule

adder.t.v
// Adder testbench
`timescale 1 ns / 1 ps
`include "adder.v"

module testFullAdder4bit();
	reg signed [4:0] a;
	reg signed [4:0] b;
    wire overflow, carryout;
    wire signed [3:0] sum; 

    FullAdder4bit adder (sum[3:0], carryout, overflow, a[3:0], b[3:0]);

    initial begin

    	$dumpfile("FullAdder4bit.vcd");
		$dumpvars(0, testFullAdder4bit);
		
		$display("Testing : ");
		$display("a  b | sum | expected sum | overflow | expected overflow");
		a = 14; b = 14; #1000
		$display("%d %d | %d |      %d      |    %d     |%d", a, b, sum, a + b, overflow, 1);

		$display("Testing : ");
		$display("a  b | sum | expected sum | overflow | expected overflow");
		a = 2; b = 8; #1000
		$display("%d %d | %d |      %d      |    %d     |%d", a, b, sum, a + b, overflow, 0);
		
		$display(" a  b | sum | overflow | carryout");
		
		for(a= -8; a < 8; a = a + 1) begin
			for(b = -8;b < 8;b = b + 1) begin
				#1000
				$display("%d %d | %d  |    %d     |   %d", a, b, sum, overflow, carryout);
			end
		end
	end
endmodule

FullAdder4bit.vcd
$date
	Thu Sep 29 01:31:23 2016
$end
$version
	Icarus Verilog
$end
$timescale
	1ps
$end
$scope module testFullAdder4bit $end
$var wire 1 ! carryout $end
$var wire 1 " overflow $end
$var wire 4 # sum [3:0] $end
$var reg 5 $ a [4:0] $end
$var reg 5 % b [4:0] $end
$scope module adder $end
$var wire 4 & a [3:0] $end
$var wire 4 ' b [3:0] $end
$var wire 1 ( carryin $end
$var wire 1 ! carryout $end
$var wire 1 ) carryout_0 $end
$var wire 1 * carryout_1 $end
$var wire 1 + carryout_2 $end
$var wire 1 " overflow $end
$var wire 4 , sum [3:0] $end
$scope module fa1 $end
$var wire 1 - a $end
$var wire 1 . aandb $end
$var wire 1 / axorb $end
$var wire 1 0 axorb_and_c $end
$var wire 1 1 b $end
$var wire 1 ( carryin $end
$var wire 1 ) carryout $end
$var wire 1 2 sum $end
$upscope $end
$scope module fa2 $end
$var wire 1 3 a $end
$var wire 1 4 aandb $end
$var wire 1 5 axorb $end
$var wire 1 6 axorb_and_c $end
$var wire 1 7 b $end
$var wire 1 ) carryin $end
$var wire 1 * carryout $end
$var wire 1 8 sum $end
$upscope $end
$scope module fa3 $end
$var wire 1 9 a $end
$var wire 1 : aandb $end
$var wire 1 ; axorb $end
$var wire 1 < axorb_and_c $end
$var wire 1 = b $end
$var wire 1 * carryin $end
$var wire 1 + carryout $end
$var wire 1 > sum $end
$upscope $end
$scope module fa4 $end
$var wire 1 ? a $end
$var wire 1 @ aandb $end
$var wire 1 A axorb $end
$var wire 1 B axorb_and_c $end
$var wire 1 C b $end
$var wire 1 + carryin $end
$var wire 1 ! carryout $end
$var wire 1 D sum $end
$upscope $end
$upscope $end
$upscope $end
$enddefinitions $end
#0
$dumpvars
xD
1C
xB
xA
x@
1?
x>
1=
x<
x;
x:
19
x8
17
x6
x5
x4
13
x2
01
z0
x/
x.
0-
bx ,
x+
x*
x)
0(
b1110 '
b1110 &
b1110 %
b1110 $
bx #
x"
x!
$end
#50000
0/
0.
05
14
0;
1:
0A
1@
00
#100000
02
bx0 #
bx0 ,
06
1*
0<
1+
0B
1!
0)
#150000
1>
1D
0"
08
b1100 #
b1100 ,
#1000000
07
0=
09
0?
b1000 '
b10 &
b1000 %
b10 $
#1050000
15
04
0:
1A
0@
#1100000
18
0*
0+
1B
0D
b110 #
b110 ,
0!
#1150000
0>
0B
1D
b1010 #
b1010 ,
1!
#1200000
0!
1"
#1250000
0"
#2000000
03
1?
b1000 &
b11000 %
b11000 $
#2050000
05
0A
1@
#2100000
08
0D
b0 #
b0 ,
1!
#2150000
1"
#3000000
11
b1001 '
b11001 %
#3050000
1/
#3100000
12
b1 #
b1 ,
#4000000
01
17
b1010 '
b11010 %
#4050000
0/
15
#4100000
02
18
b10 #
b10 ,
#5000000
11
b1011 '
b11011 %
#5050000
1/
#5100000
12
b11 #
b11 ,
#6000000
01
07
1=
b1100 '
b11100 %
#6050000
0/
05
1;
#6100000
02
08
1>
b100 #
b100 ,
#7000000
11
b1101 '
b11101 %
#7050000
1/
#7100000
12
b101 #
b101 ,
#8000000
01
17
b1110 '
b11110 %
#8050000
0/
15
#8100000
02
18
b110 #
b110 ,
#9000000
11
b1111 '
b11111 %
#9050000
1/
#9100000
12
b111 #
b111 ,
#10000000
01
07
0=
0C
b0 '
b0 %
#10050000
0/
05
0;
1A
0@
#10100000
02
08
0>
1D
b1000 #
b1000 ,
0!
#10150000
0"
#11000000
11
b1 '
b1 %
#11050000
1/
#11100000
12
b1001 #
b1001 ,
#12000000
01
17
b10 '
b10 %
#12050000
0/
15
#12100000
02
18
b1010 #
b1010 ,
#13000000
11
b11 '
b11 %
#13050000
1/
#13100000
12
b1011 #
b1011 ,
#14000000
01
07
1=
b100 '
b100 %
#14050000
0/
05
1;
#14100000
02
08
1>
b1100 #
b1100 ,
#15000000
11
b101 '
b101 %
#15050000
1/
#15100000
12
b1101 #
b1101 ,
#16000000
01
17
b110 '
b110 %
#16050000
0/
15
#16100000
02
18
b1110 #
b1110 ,
#17000000
11
b111 '
b111 %
#17050000
1/
#17100000
12
b1111 #
b1111 ,
#18000000
1-
01
07
0=
1C
b1001 &
b1000 '
b11001 $
b11000 %
#18050000
05
0;
0A
1@
#18100000
08
0>
0D
b1 #
b1 ,
1!
#18150000
1"
#19000000
11
b1001 '
b11001 %
#19050000
0/
1.
#19100000
02
b0 #
b0 ,
1)
#19150000
18
b10 #
b10 ,
#20000000
01
17
b1010 '
b11010 %
#20050000
1/
0.
15
#20100000
12
0)
16
08
b1 #
b1 ,
#20150000
06
18
b11 #
b11 ,
1*
#20200000
0*
1>
b111 #
b111 ,
#20250000
0>
b11 #
b11 ,
#21000000
11
b1011 '
b11011 %
#21050000
0/
1.
#21100000
02
b10 #
b10 ,
1)
#21150000
16
08
b0 #
b0 ,
#21200000
1*
#21250000
1>
b100 #
b100 ,
#22000000
01
07
1=
b1100 '
b11100 %
#22050000
1/
0.
05
1;
#22100000
12
0)
06
18
1<
0>
b11 #
b11 ,
#22150000
08
b1 #
b1 ,
0*
1+
#22200000
0<
1>
1D
b1101 #
b1101 ,
0"
#22250000
0+
#22300000
0D
b101 #
b101 ,
1"
#23000000
11
b1101 '
b11101 %
#23050000
0/
1.
#23100000
02
b100 #
b100 ,
1)
#23150000
18
b110 #
b110 ,
#24000000
01
17
b1110 '
b11110 %
#24050000
1/
0.
15
#24100000
12
0)
16
08
b101 #
b101 ,
#24150000
06
18
b111 #
b111 ,
1*
#24200000
0*
1<
0>
b11 #
b11 ,
#24250000
0<
1>
b111 #
b111 ,
1+
#24300000
0+
1D
b1111 #
b1111 ,
0"
#24350000
0D
b111 #
b111 ,
1"
#25000000
11
b1111 '
b11111 %
#25050000
0/
1.
#25100000
02
b110 #
b110 ,
1)
#25150000
16
08
b100 #
b100 ,
#25200000
1*
#25250000
1<
0>
b0 #
b0 ,
#25300000
1+
#25350000
1D
b1000 #
b1000 ,
0"
#26000000
01
07
0=
0C
b0 '
b0 %
#26050000
1/
0.
05
0;
1A
0@
#26100000
12
0)
06
18
0<
1>
1B
0D
b111 #
b111 ,
0!
#26150000
08
b101 #
b101 ,
0*
0+
1!
1"
#26200000
0>
0B
1D
b1001 #
b1001 ,
#26250000
0!
#26300000
0"
#27000000
11
b1 '
b1 %
#27050000
0/
1.
#27100000
02
b1000 #
b1000 ,
1)
#27150000
18
b1010 #
b1010 ,
#28000000
01
17
b10 '
b10 %
#28050000
1/
0.
15
#28100000
12
0)
16
08
b1001 #
b1001 ,
#28150000
06
18
b1011 #
b1011 ,
1*
#28200000
0*
1>
b1111 #
b1111 ,
#28250000
0>
b1011 #
b1011 ,
#29000000
11
b11 '
b11 %
#29050000
0/
1.
#29100000
02
b1010 #
b1010 ,
1)
#29150000
16
08
b1000 #
b1000 ,
#29200000
1*
#29250000
1>
b1100 #
b1100 ,
#30000000
01
07
1=
b100 '
b100 %
#30050000
1/
0.
05
1;
#30100000
12
0)
06
18
1<
0>
b1011 #
b1011 ,
#30150000
08
b1001 #
b1001 ,
0*
1+
#30200000
0<
1>
1B
0D
b101 #
b101 ,
1"
#30250000
0+
1!
#30300000
0B
1D
b1101 #
b1101 ,
#30350000
0!
#30400000
0"
#31000000
11
b101 '
b101 %
#31050000
0/
1.
#31100000
02
b1100 #
b1100 ,
1)
#31150000
18
b1110 #
b1110 ,
#32000000
01
17
b110 '
b110 %
#32050000
1/
0.
15
#32100000
12
0)
16
08
b1101 #
b1101 ,
#32150000
06
18
b1111 #
b1111 ,
1*
#32200000
0*
1<
0>
b1011 #
b1011 ,
#32250000
0<
1>
b1111 #
b1111 ,
1+
#32300000
0+
1B
0D
b111 #
b111 ,
1"
#32350000
0B
1D
b1111 #
b1111 ,
0"
1!
#32400000
0!
1"
#32450000
0"
#33000000
11
b111 '
b111 %
#33050000
0/
1.
#33100000
02
b1110 #
b1110 ,
1)
#33150000
16
08
b1100 #
b1100 ,
#33200000
1*
#33250000
1<
0>
b1000 #
b1000 ,
#33300000
1+
#33350000
1B
0D
b0 #
b0 ,
1"
#33400000
1!
#33450000
0"
#34000000
0-
13
01
07
0=
1C
b1010 &
b1000 '
b11010 $
b11000 %
#34050000
0.
0;
0A
1@
#34100000
0)
0<
1>
0B
1D
b1100 #
b1100 ,
#34150000
06
18
b1110 #
b1110 ,
0+
#34200000
0*
0D
b110 #
b110 ,
1"
#34250000
0>
b10 #
b10 ,
#35000000
11
b1001 '
b11001 %
#35050000
1/
#35100000
12
b11 #
b11 ,
#36000000
01
17
b1010 '
b11010 %
#36050000
0/
05
14
#36100000
02
08
b0 #
b0 ,
1*
#36150000
1>
b100 #
b100 ,
#37000000
11
b1011 '
b11011 %
#37050000
1/
#37100000
12
b101 #
b101 ,
#38000000
01
07
1=
b1100 '
b11100 %
#38050000
0/
15
04
1;
#38100000
02
18
0*
1<
0>
b10 #
b10 ,
#38150000
0<
1>
b110 #
b110 ,
1+
#38200000
0+
1D
b1110 #
b1110 ,
0"
#38250000
0D
b110 #
b110 ,
1"
#39000000
11
b1101 '
b11101 %
#39050000
1/
#39100000
12
b111 #
b111 ,
#40000000
01
17
b1110 '
b11110 %
#40050000
0/
05
14
#40100000
02
08
b100 #
b100 ,
1*
#40150000
1<
0>
b0 #
b0 ,
#40200000
1+
#40250000
1D
b1000 #
b1000 ,
0"
#41000000
11
b1111 '
b11111 %
#41050000
1/
#41100000
12
b1001 #
b1001 ,
#42000000
01
07
0=
0C
b0 '
b0 %
#42050000
0/
15
04
0;
1A
0@
#42100000
02
18
0*
0<
1>
1B
0D
b110 #
b110 ,
0!
#42150000
0>
b10 #
b10 ,
0+
1!
1"
#42200000
0B
1D
b1010 #
b1010 ,
#42250000
0!
#42300000
0"
#43000000
11
b1 '
b1 %
#43050000
1/
#43100000
12
b1011 #
b1011 ,
#44000000
01
17
b10 '
b10 %
#44050000
0/
05
14
#44100000
02
08
b1000 #
b1000 ,
1*
#44150000
1>
b1100 #
b1100 ,
#45000000
11
b11 '
b11 %
#45050000
1/
#45100000
12
b1101 #
b1101 ,
#46000000
01
07
1=
b100 '
b100 %
#46050000
0/
15
04
1;
#46100000
02
18
0*
1<
0>
b1010 #
b1010 ,
#46150000
0<
1>
b1110 #
b1110 ,
1+
#46200000
0+
1B
0D
b110 #
b110 ,
1"
#46250000
0B
1D
b1110 #
b1110 ,
0"
1!
#46300000
0!
1"
#46350000
0"
#47000000
11
b101 '
b101 %
#47050000
1/
#47100000
12
b1111 #
b1111 ,
#48000000
01
17
b110 '
b110 %
#48050000
0/
05
14
#48100000
02
08
b1100 #
b1100 ,
1*
#48150000
1<
0>
b1000 #
b1000 ,
#48200000
1+
#48250000
1B
0D
b0 #
b0 ,
1"
#48300000
1!
#48350000
0"
#49000000
11
b111 '
b111 %
#49050000
1/
#49100000
12
b1 #
b1 ,
#50000000
1-
01
07
0=
1C
b1011 &
b1000 '
b11011 $
b11000 %
#50050000
15
04
0;
0A
1@
#50100000
18
0*
0<
1>
0B
1D
b1111 #
b1111 ,
#50150000
0>
b1011 #
b1011 ,
0+
#50200000
0D
b11 #
b11 ,
1"
#51000000
11
b1001 '
b11001 %
#51050000
0/
1.
#51100000
02
b10 #
b10 ,
1)
#51150000
16
08
b0 #
b0 ,
#51200000
1*
#51250000
1>
b100 #
b100 ,
#52000000
01
17
b1010 '
b11010 %
#52050000
1/
0.
05
14
#52100000
12
0)
06
18
b111 #
b111 ,
#52150000
08
b101 #
b101 ,
#53000000
11
b1011 '
b11011 %
#53050000
0/
1.
#53100000
02
b100 #
b100 ,
1)
#53150000
18
b110 #
b110 ,
#54000000
01
07
1=
b1100 '
b11100 %
#54050000
1/
0.
15
04
1;
#54100000
12
0)
16
08
0*
1<
0>
b1 #
b1 ,
#54150000
06
18
1*
0<
1>
b111 #
b111 ,
1+
#54200000
0*
1<
0>
0+
1D
b1011 #
b1011 ,
0"
#54250000
0<
1>
1+
0D
b111 #
b111 ,
1"
#54300000
0+
1D
b1111 #
b1111 ,
0"
#54350000
0D
b111 #
b111 ,
1"
#55000000
11
b1101 '
b11101 %
#55050000
0/
1.
#55100000
02
b110 #
b110 ,
1)
#55150000
16
08
b100 #
b100 ,
#55200000
1*
#55250000
1<
0>
b0 #
b0 ,
#55300000
1+
#55350000
1D
b1000 #
b1000 ,
0"
#56000000
01
17
b1110 '
b11110 %
#56050000
1/
0.
05
14
#56100000
12
0)
06
18
b1011 #
b1011 ,
#56150000
08
b1001 #
b1001 ,
#57000000
11
b1111 '
b11111 %
#57050000
0/
1.
#57100000
02
b1000 #
b1000 ,
1)
#57150000
18
b1010 #
b1010 ,
#58000000
01
07
0=
0C
b0 '
b0 %
#58050000
1/
0.
15
04
0;
1A
0@
#58100000
12
0)
16
08
0*
0<
1>
1B
0D
b101 #
b101 ,
0!
#58150000
06
18
1*
0>
b11 #
b11 ,
0+
1!
1"
#58200000
0*
1>
0B
1D
b1111 #
b1111 ,
#58250000
0>
b1011 #
b1011 ,
0!
#58300000
0"
#59000000
11
b1 '
b1 %
#59050000
0/
1.
#59100000
02
b1010 #
b1010 ,
1)
#59150000
16
08
b1000 #
b1000 ,
#59200000
1*
#59250000
1>
b1100 #
b1100 ,
#60000000
01
17
b10 '
b10 %
#60050000
1/
0.
05
14
#60100000
12
0)
06
18
b1111 #
b1111 ,
#60150000
08
b1101 #
b1101 ,
#61000000
11
b11 '
b11 %
#61050000
0/
1.
#61100000
02
b1100 #
b1100 ,
1)
#61150000
18
b1110 #
b1110 ,
#62000000
01
07
1=
b100 '
b100 %
#62050000
1/
0.
15
04
1;
#62100000
12
0)
16
08
0*
1<
0>
b1001 #
b1001 ,
#62150000
06
18
1*
0<
1>
b1111 #
b1111 ,
1+
#62200000
0*
1<
0>
0+
1B
0D
b11 #
b11 ,
1"
#62250000
0<
1>
1+
0B
1D
b1111 #
b1111 ,
0"
1!
#62300000
0+
1B
0D
b111 #
b111 ,
0!
#62350000
0B
1D
b1111 #
b1111 ,
1!
#62400000
0!
1"
#62450000
0"
#63000000
11
b101 '
b101 %
#63050000
0/
1.
#63100000
02
b1110 #
b1110 ,
1)
#63150000
16
08
b1100 #
b1100 ,
#63200000
1*
#63250000
1<
0>
b1000 #
b1000 ,
#63300000
1+
#63350000
1B
0D
b0 #
b0 ,
1"
#63400000
1!
#63450000
0"
#64000000
01
17
b110 '
b110 %
#64050000
1/
0.
05
14
#64100000
12
0)
06
18
b11 #
b11 ,
#64150000
08
b1 #
b1 ,
#65000000
11
b111 '
b111 %
#65050000
0/
1.
#65100000
02
b0 #
b0 ,
1)
#65150000
18
b10 #
b10 ,
#66000000
0-
03
19
01
07
0=
1C
b1100 &
b1000 '
b11100 $
b11000 %
#66050000
0.
04
0A
1@
#66100000
0)
0*
0B
1D
b1010 #
b1010 ,
#66150000
08
0<
1>
b1100 #
b1100 ,
#66200000
0+
#66250000
0D
b100 #
b100 ,
1"
#67000000
11
b1001 '
b11001 %
#67050000
1/
#67100000
12
b101 #
b101 ,
#68000000
01
17
b1010 '
b11010 %
#68050000
0/
15
#68100000
02
18
b110 #
b110 ,
#69000000
11
b1011 '
b11011 %
#69050000
1/
#69100000
12
b111 #
b111 ,
#70000000
01
07
1=
b1100 '
b11100 %
#70050000
0/
05
0;
1:
#70100000
02
08
0>
b0 #
b0 ,
1+
#70150000
1D
b1000 #
b1000 ,
0"
#71000000
11
b1101 '
b11101 %
#71050000
1/
#71100000
12
b1001 #
b1001 ,
#72000000
01
17
b1110 '
b11110 %
#72050000
0/
15
#72100000
02
18
b1010 #
b1010 ,
#73000000
11
b1111 '
b11111 %
#73050000
1/
#73100000
12
b1011 #
b1011 ,
#74000000
01
07
0=
0C
b0 '
b0 %
#74050000
0/
05
1;
0:
1A
0@
#74100000
02
08
1>
0+
1B
0D
b100 #
b100 ,
0!
#74150000
0B
1D
b1100 #
b1100 ,
1!
#74200000
0!
1"
#74250000
0"
#75000000
11
b1 '
b1 %
#75050000
1/
#75100000
12
b1101 #
b1101 ,
#76000000
01
17
b10 '
b10 %
#76050000
0/
15
#76100000
02
18
b1110 #
b1110 ,
#77000000
11
b11 '
b11 %
#77050000
1/
#77100000
12
b1111 #
b1111 ,
#78000000
01
07
1=
b100 '
b100 %
#78050000
0/
05
0;
1:
#78100000
02
08
0>
b1000 #
b1000 ,
1+
#78150000
1B
0D
b0 #
b0 ,
1"
#78200000
1!
#78250000
0"
#79000000
11
b101 '
b101 %
#79050000
1/
#79100000
12
b1 #
b1 ,
#80000000
01
17
b110 '
b110 %
#80050000
0/
15
#80100000
02
18
b10 #
b10 ,
#81000000
11
b111 '
b111 %
#81050000
1/
#81100000
12
b11 #
b11 ,
#82000000
1-
01
07
0=
1C
b1101 &
b1000 '
b11101 $
b11000 %
#82050000
05
1;
0:
0A
1@
#82100000
08
1>
0+
0B
1D
b1101 #
b1101 ,
#82150000
0D
b101 #
b101 ,
1"
#83000000
11
b1001 '
b11001 %
#83050000
0/
1.
#83100000
02
b100 #
b100 ,
1)
#83150000
18
b110 #
b110 ,
#84000000
01
17
b1010 '
b11010 %
#84050000
1/
0.
15
#84100000
12
0)
16
08
b101 #
b101 ,
#84150000
06
18
b111 #
b111 ,
1*
#84200000
0*
1<
0>
b11 #
b11 ,
#84250000
0<
1>
b111 #
b111 ,
1+
#84300000
0+
1D
b1111 #
b1111 ,
0"
#84350000
0D
b111 #
b111 ,
1"
#85000000
11
b1011 '
b11011 %
#85050000
0/
1.
#85100000
02
b110 #
b110 ,
1)
#85150000
16
08
b100 #
b100 ,
#85200000
1*
#85250000
1<
0>
b0 #
b0 ,
#85300000
1+
#85350000
1D
b1000 #
b1000 ,
0"
#86000000
01
07
1=
b1100 '
b11100 %
#86050000
1/
0.
05
0;
1:
#86100000
12
0)
06
18
0<
1>
b1111 #
b1111 ,
#86150000
08
b1101 #
b1101 ,
0*
#86200000
0>
b1001 #
b1001 ,
#87000000
11
b1101 '
b11101 %
#87050000
0/
1.
#87100000
02
b1000 #
b1000 ,
1)
#87150000
18
b1010 #
b1010 ,
#88000000
01
17
b1110 '
b11110 %
#88050000
1/
0.
15
#88100000
12
0)
16
08
b1001 #
b1001 ,
#88150000
06
18
b1011 #
b1011 ,
1*
#88200000
0*
1>
b1111 #
b1111 ,
#88250000
0>
b1011 #
b1011 ,
#89000000
11
b1111 '
b11111 %
#89050000
0/
1.
#89100000
02
b1010 #
b1010 ,
1)
#89150000
16
08
b1000 #
b1000 ,
#89200000
1*
#89250000
1>
b1100 #
b1100 ,
#90000000
01
07
0=
0C
b0 '
b0 %
#90050000
1/
0.
05
1;
0:
1A
0@
#90100000
12
0)
06
18
1<
0>
0+
1B
0D
b11 #
b11 ,
0!
#90150000
08
0*
1+
0B
1D
b1001 #
b1001 ,
1!
#90200000
0<
1>
1B
0D
b101 #
b101 ,
0!
#90250000
0+
1!
1"
#90300000
0B
1D
b1101 #
b1101 ,
#90350000
0!
#90400000
0"
#91000000
11
b1 '
b1 %
#91050000
0/
1.
#91100000
02
b1100 #
b1100 ,
1)
#91150000
18
b1110 #
b1110 ,
#92000000
01
17
b10 '
b10 %
#92050000
1/
0.
15
#92100000
12
0)
16
08
b1101 #
b1101 ,
#92150000
06
18
b1111 #
b1111 ,
1*
#92200000
0*
1<
0>
b1011 #
b1011 ,
#92250000
0<
1>
b1111 #
b1111 ,
1+
#92300000
0+
1B
0D
b111 #
b111 ,
1"
#92350000
0B
1D
b1111 #
b1111 ,
0"
1!
#92400000
0!
1"
#92450000
0"
#93000000
11
b11 '
b11 %
#93050000
0/
1.
#93100000
02
b1110 #
b1110 ,
1)
#93150000
16
08
b1100 #
b1100 ,
#93200000
1*
#93250000
1<
0>
b1000 #
b1000 ,
#93300000
1+
#93350000
1B
0D
b0 #
b0 ,
1"
#93400000
1!
#93450000
0"
#94000000
01
07
1=
b100 '
b100 %
#94050000
1/
0.
05
0;
1:
#94100000
12
0)
06
18
0<
1>
b111 #
b111 ,
#94150000
08
b101 #
b101 ,
0*
#94200000
0>
b1 #
b1 ,
#95000000
11
b101 '
b101 %
#95050000
0/
1.
#95100000
02
b0 #
b0 ,
1)
#95150000
18
b10 #
b10 ,
#96000000
01
17
b110 '
b110 %
#96050000
1/
0.
15
#96100000
12
0)
16
08
b1 #
b1 ,
#96150000
06
18
b11 #
b11 ,
1*
#96200000
0*
1>
b111 #
b111 ,
#96250000
0>
b11 #
b11 ,
#97000000
11
b111 '
b111 %
#97050000
0/
1.
#97100000
02
b10 #
b10 ,
1)
#97150000
16
08
b0 #
b0 ,
#97200000
1*
#97250000
1>
b100 #
b100 ,
#98000000
0-
13
01
07
0=
1C
b1110 &
b1000 '
b11110 $
b11000 %
#98050000
0.
1;
0:
0A
1@
#98100000
0)
1<
0>
0+
0B
1D
b1000 #
b1000 ,
#98150000
06
18
1+
0D
b10 #
b10 ,
1"
#98200000
0*
1D
b1010 #
b1010 ,
0"
#98250000
0<
1>
b1110 #
b1110 ,
#98300000
0+
#98350000
0D
b110 #
b110 ,
1"
#99000000
11
b1001 '
b11001 %
#99050000
1/
#99100000
12
b111 #
b111 ,
#100000000
01
17
b1010 '
b11010 %
#100050000
0/
05
14
#100100000
02
08
b100 #
b100 ,
1*
#100150000
1<
0>
b0 #
b0 ,
#100200000
1+
#100250000
1D
b1000 #
b1000 ,
0"
#101000000
11
b1011 '
b11011 %
#101050000
1/
#101100000
12
b1001 #
b1001 ,
#102000000
01
07
1=
b1100 '
b11100 %
#102050000
0/
15
04
0;
1:
#102100000
02
18
0*
0<
1>
b1110 #
b1110 ,
#102150000
0>
b1010 #
b1010 ,
#103000000
11
b1101 '
b11101 %
#103050000
1/
#103100000
12
b1011 #
b1011 ,
#104000000
01
17
b1110 '
b11110 %
#104050000
0/
05
14
#104100000
02
08
b1000 #
b1000 ,
1*
#104150000
1>
b1100 #
b1100 ,
#105000000
11
b1111 '
b11111 %
#105050000
1/
#105100000
12
b1101 #
b1101 ,
#106000000
01
07
0=
0C
b0 '
b0 %
#106050000
0/
15
04
1;
0:
1A
0@
#106100000
02
18
0*
1<
0>
0+
1B
0D
b10 #
b10 ,
0!
#106150000
0<
1>
1+
0B
1D
b1110 #
b1110 ,
1!
#106200000
0+
1B
0D
b110 #
b110 ,
0!
#106250000
0B
1D
b1110 #
b1110 ,
1!
#106300000
0!
1"
#106350000
0"
#107000000
11
b1 '
b1 %
#107050000
1/
#107100000
12
b1111 #
b1111 ,
#108000000
01
17
b10 '
b10 %
#108050000
0/
05
14
#108100000
02
08
b1100 #
b1100 ,
1*
#108150000
1<
0>
b1000 #
b1000 ,
#108200000
1+
#108250000
1B
0D
b0 #
b0 ,
1"
#108300000
1!
#108350000
0"
#109000000
11
b11 '
b11 %
#109050000
1/
#109100000
12
b1 #
b1 ,
#110000000
01
07
1=
b100 '
b100 %
#110050000
0/
15
04
0;
1:
#110100000
02
18
0*
0<
1>
b110 #
b110 ,
#110150000
0>
b10 #
b10 ,
#111000000
11
b101 '
b101 %
#111050000
1/
#111100000
12
b11 #
b11 ,
#112000000
01
17
b110 '
b110 %
#112050000
0/
05
14
#112100000
02
08
b0 #
b0 ,
1*
#112150000
1>
b100 #
b100 ,
#113000000
11
b111 '
b111 %
#113050000
1/
#113100000
12
b101 #
b101 ,
#114000000
1-
01
07
0=
1C
b1111 &
b1000 '
b11111 $
b11000 %
#114050000
15
04
1;
0:
0A
1@
#114100000
18
0*
1<
0>
0+
0B
1D
b1011 #
b1011 ,
#114150000
0<
1>
1+
0D
b111 #
b111 ,
1"
#114200000
0+
1D
b1111 #
b1111 ,
0"
#114250000
0D
b111 #
b111 ,
1"
#115000000
11
b1001 '
b11001 %
#115050000
0/
1.
#115100000
02
b110 #
b110 ,
1)
#115150000
16
08
b100 #
b100 ,
#115200000
1*
#115250000
1<
0>
b0 #
b0 ,
#115300000
1+
#115350000
1D
b1000 #
b1000 ,
0"
#116000000
01
17
b1010 '
b11010 %
#116050000
1/
0.
05
14
#116100000
12
0)
06
18
b1011 #
b1011 ,
#116150000
08
b1001 #
b1001 ,
#117000000
11
b1011 '
b11011 %
#117050000
0/
1.
#117100000
02
b1000 #
b1000 ,
1)
#117150000
18
b1010 #
b1010 ,
#118000000
01
07
1=
b1100 '
b11100 %
#118050000
1/
0.
15
04
0;
1:
#118100000
12
0)
16
08
0*
0<
1>
b1101 #
b1101 ,
#118150000
06
18
1*
0>
b1011 #
b1011 ,
#118200000
0*
1>
b1111 #
b1111 ,
#118250000
0>
b1011 #
b1011 ,
#119000000
11
b1101 '
b11101 %
#119050000
0/
1.
#119100000
02
b1010 #
b1010 ,
1)
#119150000
16
08
b1000 #
b1000 ,
#119200000
1*
#119250000
1>
b1100 #
b1100 ,
#120000000
01
17
b1110 '
b11110 %
#120050000
1/
0.
05
14
#120100000
12
0)
06
18
b1111 #
b1111 ,
#120150000
08
b1101 #
b1101 ,
#121000000
11
b1111 '
b11111 %
#121050000
0/
1.
#121100000
02
b1100 #
b1100 ,
1)
#121150000
18
b1110 #
b1110 ,
#122000000
01
07
0=
0C
b0 '
b0 %
#122050000
1/
0.
15
04
1;
0:
1A
0@
#122100000
12
0)
16
08
0*
1<
0>
0+
1B
0D
b1 #
b1 ,
0!
#122150000
06
18
1*
0<
1>
1+
0B
1D
b1111 #
b1111 ,
1!
#122200000
0*
1<
0>
0+
1B
0D
b11 #
b11 ,
0!
#122250000
0<
1>
1+
0B
1D
b1111 #
b1111 ,
1!
#122300000
0+
1B
0D
b111 #
b111 ,
0!
#122350000
0B
1D
b1111 #
b1111 ,
1!
#122400000
0!
1"
#122450000
0"
#123000000
11
b1 '
b1 %
#123050000
0/
1.
#123100000
02
b1110 #
b1110 ,
1)
#123150000
16
08
b1100 #
b1100 ,
#123200000
1*
#123250000
1<
0>
b1000 #
b1000 ,
#123300000
1+
#123350000
1B
0D
b0 #
b0 ,
1"
#123400000
1!
#123450000
0"
#124000000
01
17
b10 '
b10 %
#124050000
1/
0.
05
14
#124100000
12
0)
06
18
b11 #
b11 ,
#124150000
08
b1 #
b1 ,
#125000000
11
b11 '
b11 %
#125050000
0/
1.
#125100000
02
b0 #
b0 ,
1)
#125150000
18
b10 #
b10 ,
#126000000
01
07
1=
b100 '
b100 %
#126050000
1/
0.
15
04
0;
1:
#126100000
12
0)
16
08
0*
0<
1>
b101 #
b101 ,
#126150000
06
18
1*
0>
b11 #
b11 ,
#126200000
0*
1>
b111 #
b111 ,
#126250000
0>
b11 #
b11 ,
#127000000
11
b101 '
b101 %
#127050000
0/
1.
#127100000
02
b10 #
b10 ,
1)
#127150000
16
08
b0 #
b0 ,
#127200000
1*
#127250000
1>
b100 #
b100 ,
#128000000
01
17
b110 '
b110 %
#128050000
1/
0.
05
14
#128100000
12
0)
06
18
b111 #
b111 ,
#128150000
08
b101 #
b101 ,
#129000000
11
b111 '
b111 %
#129050000
0/
1.
#129100000
02
b100 #
b100 ,
1)
#129150000
18
b110 #
b110 ,
#130000000
0-
03
09
0?
01
07
0=
1C
b0 &
b1000 '
b0 $
b11000 %
#130050000
0.
04
0:
#130100000
0)
0*
0+
#130150000
08
0>
0B
1D
b1000 #
b1000 ,
1"
#130200000
0!
#130250000
0"
#131000000
11
b1001 '
b11001 %
#131050000
1/
#131100000
12
b1001 #
b1001 ,
#132000000
01
17
b1010 '
b11010 %
#132050000
0/
15
#132100000
02
18
b1010 #
b1010 ,
#133000000
11
b1011 '
b11011 %
#133050000
1/
#133100000
12
b1011 #
b1011 ,
#134000000
01
07
1=
b1100 '
b11100 %
