adder.v
// Adder circuit

// define gates with delays
`define AND and #50
`define OR or #50
`define NOT not #50
`define XNOR xnor #50
`define XOR xor #50

module structuralFullAdder
(
  output sum,
  output carryout,
  input a,
  input b,
  input carryin
);
  wire na, nb, nc;
  `NOT not0(na, a);
  `NOT not1(nb, b);
  `NOT not2(nc, carryin);

  wire na_b_nc, na_nb_c, a_b_c, a_nb_nc;
  `AND and0(na_b_nc, na, b, nc);
  `AND and1(na_nb_c, na, nb, carryin);
  `AND and2(a_b_c, a, b, carryin);
  `AND and3(a_nb_nc, a, nb, nc);

  `OR or0(sum, na_b_nc, na_nb_c, a_b_c, a_nb_nc);

  wire a_b, b_c, a_c;
  `AND and4(a_b, a, b);
  `AND and5(b_c, b, carryin);
  `AND and6(a_c, a, carryin);

  `OR or1(carryout, a_b, b_c, a_c);
endmodule

module FullAdder4bit
(
  output[3:0] sum,  // 2's complement sum of a and b
  output carryout,  // Carry out of the summation of a and b
  output overflow,  // True if the calculation resulted in an overflow
  input[3:0] a,     // First operand in 2's complement format
  input[3:0] b      // Second operand in 2's complement format
);
  wire cin;
  assign cin = 1'b0;
  structuralFullAdder a0(.sum(sum[0]), .carryout(cout0), .a(a[0]), .b(b[0]), .carryin(cin));
  structuralFullAdder a1(.sum(sum[1]), .carryout(cout1), .a(a[1]), .b(b[1]), .carryin(cout0));
  structuralFullAdder a2(.sum(sum[2]), .carryout(cout2), .a(a[2]), .b(b[2]), .carryin(cout1));
  structuralFullAdder a3(.sum(sum[3]), .carryout(carryout), .a(a[3]), .b(b[3]), .carryin(cout2));

  wire same_sign, switched;
  `XNOR xnor0(same_sign, a[3], b[3]);
  `XOR xor0(switched, sum[3], a[3]);
  `AND and0(overflow, same_sign, switched);
endmodule

adder.t.v
// Adder testbench
`timescale 1 ns / 1 ps
`include "adder.v"

module testFullAdder4bit();
  reg[3:0] opA, opB;       // Stored inputs to adder
  wire[3:0] res0, res1;     // Output display options
  wire res_sel;             // Select between display options
  wire cout;                // Carry out from adder
  wire ovf;                 // Overflow from adder

  FullAdder4bit adder(.sum(res0), .carryout(cout), .overflow(ovf), .a(opA), .b(opB));

  initial begin
    // $dumpfile("testFullAdder4bit.vcd");
    // $dumpvars(0, testFullAdder4bit);

    $display("  A     B    |   Sum  Co  Ovf | Expected Output");

    //No carryout, no overflow
    opA=0; opB=0; #1000;
    $display(" %b  %b  |  %b  %b    %b  | 0000 0 0", opA, opB, res0, cout, ovf);
    opA=1; opB=1; #1000;
    $display(" %b  %b  |  %b  %b    %b  | 0010 0 0", opA, opB, res0, cout, ovf);
    opA=3; opB=4; #1000;
    $display(" %b  %b  |  %b  %b    %b  | 0111 0 0", opA, opB, res0, cout, ovf);
    opA=1; opB=-7; #1000;
    $display(" %b  %b  |  %b  %b    %b  | 1010 0 0", opA, opB, res0, cout, ovf);

    $display("-----------------------------------------------");

    //Carryout, no overflow
    opA=-4; opB=-4; #1000;
    $display(" %b  %b  |  %b  %b    %b  | 1000 1 0", opA, opB, res0, cout, ovf);
    opA=-1; opB=-1; #1000;
    $display(" %b  %b  |  %b  %b    %b  | 1110 1 0", opA, opB, res0, cout, ovf);
    opA=6; opB=-1; #1000;
    $display(" %b  %b  |  %b  %b    %b  | 0101 1 0", opA, opB, res0, cout, ovf);
    opA=4; opB=-4; #1000;
    $display(" %b  %b  |  %b  %b    %b  | 0000 1 0", opA, opB, res0, cout, ovf);

    $display("-----------------------------------------------");

    //No carryout, overflow
    opA=4; opB=4; #1000;
    $display(" %b  %b  |  %b  %b    %b  | 1000 0 1", opA, opB, res0, cout, ovf);
    opA=7; opB=7; #1000;
    $display(" %b  %b  |  %b  %b    %b  | 1110 0 1", opA, opB, res0, cout, ovf);
    opA=6; opB=7; #1000;
    $display(" %b  %b  |  %b  %b    %b  | 1101 0 1", opA, opB, res0, cout, ovf);
    opA=5; opB=6; #1000;
    $display(" %b  %b  |  %b  %b    %b  | 1011 0 1", opA, opB, res0, cout, ovf);

    $display("-----------------------------------------------");

    //Carryout, overflow
    opA=-8; opB=-8; #1000;
    $display(" %b  %b  |  %b  %b    %b  | 0000 1 1", opA, opB, res0, cout, ovf);
    opA=-8; opB=-1; #1000;
    $display(" %b  %b  |  %b  %b    %b  | 0111 1 1", opA, opB, res0, cout, ovf);
    opA=-6; opB=-7; #1000;
    $display(" %b  %b  |  %b  %b    %b  | 0011 1 1", opA, opB, res0, cout, ovf);
    opA=-5; opB=-6; #1000;
    $display(" %b  %b  |  %b  %b    %b  | 0101 1 1", opA, opB, res0, cout, ovf);

    // for (i = 0; i < 16; i = i +1) begin
    //   $display ("Current value of i is %d", i);
    // end

  end

endmodule

testFullAdder4bit.vcd
$date
	Wed Sep 28 02:35:12 2016
$end
$version
	Icarus Verilog
$end
$timescale
	1ps
$end
$scope module testFullAdder4bit $end
$var wire 1 ! cout $end
$var wire 1 " ovf $end
$var wire 4 # res0 [3:0] $end
$var reg 4 $ opA [3:0] $end
$var reg 4 % opB [3:0] $end
$scope module adder $end
$var wire 4 & a [3:0] $end
$var wire 4 ' b [3:0] $end
$var wire 1 ! carryout $end
$var wire 1 ( cin $end
$var wire 1 ) cout0 $end
$var wire 1 * cout1 $end
$var wire 1 + cout2 $end
$var wire 1 " overflow $end
$var wire 1 , same_sign $end
$var wire 4 - sum [3:0] $end
$var wire 1 . switched $end
$scope module a0 $end
$var wire 1 / a $end
$var wire 1 0 a_b $end
$var wire 1 1 a_b_c $end
$var wire 1 2 a_c $end
$var wire 1 3 a_nb_nc $end
$var wire 1 4 b $end
$var wire 1 5 b_c $end
$var wire 1 ( carryin $end
$var wire 1 ) carryout $end
$var wire 1 6 na $end
$var wire 1 7 na_b_nc $end
$var wire 1 8 na_nb_c $end
$var wire 1 9 nb $end
$var wire 1 : nc $end
$var wire 1 ; sum $end
$upscope $end
$scope module a1 $end
$var wire 1 < a $end
$var wire 1 = a_b $end
$var wire 1 > a_b_c $end
$var wire 1 ? a_c $end
$var wire 1 @ a_nb_nc $end
$var wire 1 A b $end
$var wire 1 B b_c $end
$var wire 1 ) carryin $end
$var wire 1 * carryout $end
$var wire 1 C na $end
$var wire 1 D na_b_nc $end
$var wire 1 E na_nb_c $end
$var wire 1 F nb $end
$var wire 1 G nc $end
$var wire 1 H sum $end
$upscope $end
$scope module a2 $end
$var wire 1 I a $end
$var wire 1 J a_b $end
$var wire 1 K a_b_c $end
$var wire 1 L a_c $end
$var wire 1 M a_nb_nc $end
$var wire 1 N b $end
$var wire 1 O b_c $end
$var wire 1 * carryin $end
$var wire 1 + carryout $end
$var wire 1 P na $end
$var wire 1 Q na_b_nc $end
$var wire 1 R na_nb_c $end
$var wire 1 S nb $end
$var wire 1 T nc $end
$var wire 1 U sum $end
$upscope $end
$scope module a3 $end
$var wire 1 V a $end
$var wire 1 W a_b $end
$var wire 1 X a_b_c $end
$var wire 1 Y a_c $end
$var wire 1 Z a_nb_nc $end
$var wire 1 [ b $end
$var wire 1 \ b_c $end
$var wire 1 + carryin $end
$var wire 1 ! carryout $end
$var wire 1 ] na $end
$var wire 1 ^ na_b_nc $end
$var wire 1 _ na_nb_c $end
$var wire 1 ` nb $end
$var wire 1 a nc $end
$var wire 1 b sum $end
$upscope $end
$upscope $end
$upscope $end
$enddefinitions $end
#0
$dumpvars
zb
xa
z`
x_
z^
z]
z\
0[
zZ
zY
zX
zW
0V
zU
xT
zS
xR
zQ
zP
zO
0N
zM
zL
zK
zJ
0I
zH
xG
zF
xE
zD
zC
zB
0A
z@
z?
z>
z=
0<
z;
z:
z9
z8
z7
z6
z5
04
z3
z2
z1
z0
0/
x.
bz -
z,
x+
x*
x)
0(
b0 '
b0 &
b0 %
b0 $
bz #
x"
x!
$end
#50000
xb
xU
xH
bxz #
bxz -
16
1C
1P
1]
19
1F
1S
1`
0Y
0\
0W
0Z
0X
0^
0L
0O
0J
0M
0K
0Q
0?
0B
0=
0@
0>
0D
02
05
00
03
01
08
07
1:
1,
#100000
0!
0+
0*
0)
0;
bx0 #
bx0 -
#150000
1a
0_
1T
0R
1G
0E
#200000
0b
0U
0H
b0 #
b0 -
#250000
0.
#300000
0"
#1000000
14
1/
b1 %
b1 '
b1 $
b1 &
#1050000
09
17
06
13
10
#1100000
03
07
1;
b1 #
b1 -
1)
#1150000
0;
b0 #
b0 -
0G
1E
#1200000
1H
b10 #
b10 -
#2000000
04
1N
1<
b100 %
b100 '
b11 $
b11 &
#2050000
19
00
0S
1Q
0C
1?
#2100000
13
0)
1U
b110 #
b110 -
0E
1*
#2150000
1;
1G
0?
0H
b101 #
b101 -
0T
1O
#2200000
1@
0*
0Q
1+
#2250000
1H
1T
0O
0U
b11 #
b11 -
0a
1_
#2300000
1Q
0+
1b
b1011 #
b1011 -
#2350000
1.
1U
b1111 #
b1111 -
1a
0_
#2400000
1"
0b
b111 #
b111 -
#2450000
0.
#2500000
0"
#3000000
14
0N
1[
0<
b1001 %
b1001 '
b1 $
b1 &
#3050000
09
10
1S
0Q
0`
1^
0,
1C
0@
#3100000
03
1)
0U
1b
0H
b1001 #
b1001 -
#3150000
1.
0;
b1000 #
b1000 -
0G
1E
#3200000
1H
b1010 #
b1010 -
#4000000
04
1N
0/
1I
1V
b1100 %
b1100 '
b1100 $
b1100 &
#4050000
19
0S
1Q
16
00
0P
1M
1J
0]
1W
1,
0.
#4100000
0M
0)
0Q
1U
b1110 #
b1110 -
1+
0^
1!
#4150000
1G
0E
0U
0a
1X
1\
1Y
0b
b10 #
b10 -
#4200000
1.
0H
1b
b1000 #
b1000 -
#4250000
0.
1"
#4300000
0"
#5000000
14
1A
1/
1<
b1111 %
b1111 '
b1111 $
b1111 &
#5050000
09
17
0F
1D
06
13
10
0C
1@
1=
#5100000
03
0@
07
1;
1)
0D
1H
b1011 #
b1011 -
1*
#5150000
0;
0G
1>
1B
1?
0H
b1000 #
b1000 -
0T
1K
1O
1L
#5200000
1H
1U
b1110 #
b1110 -
#6000000
0/
0V
b110 $
b110 &
#6050000
16
00
1]
0X
0W
0Y
0,
1.
#6100000
17
0)
0b
b110 #
b110 -
#6150000
0.
1;
b111 #
b111 -
1G
0>
0B
0?
#6200000
0H
b101 #
b101 -
#7000000
04
0A
0<
b1100 %
b1100 '
b100 $
b100 &
#7050000
19
07
1F
1C
0=
#7100000
0;
b100 #
b100 -
0*
#7150000
1T
0K
0O
0L
#7200000
0U
b0 #
b0 -
#8000000
0[
b100 %
b100 '
#8050000
1`
0\
1,
#8100000
1_
0!
#8150000
1b
b1000 #
b1000 -
#8200000
1.
#8250000
1"
#9000000
14
1A
1/
1<
b111 %
b111 '
b111 $
b111 &
#9050000
09
17
0F
1D
06
13
10
0C
1@
1=
#9100000
03
0@
07
1;
1)
0D
1H
b1011 #
b1011 -
1*
#9150000
0;
0G
1>
1B
1?
0H
b1000 #
b1000 -
0T
1K
1O
1L
#9200000
1H
1U
b1110 #
b1110 -
#10000000
0/
b110 $
b110 &
#10050000
16
00
#10100000
17
0)
#10150000
1;
b1111 #
b1111 -
1G
0>
0B
0?
#10200000
0H
b1101 #
b1101 -
#11000000
04
1/
0<
b110 %
b110 '
b101 $
b101 &
#11050000
19
07
06
1C
0=
#11100000
13
0;
b1100 #
b1100 -
1D
0*
#11150000
1;
1H
b1111 #
b1111 -
1T
0K
0O
0L
#11200000
0U
b1011 #
b1011 -
#12000000
0A
0N
1[
0/
0I
1V
b1000 %
b1000 '
b1000 $
b1000 &
#12050000
1F
0D
1S
0`
1\
16
03
1P
0J
0]
1X
1W
1Y
0.
#12100000
0H
0;
b1000 #
b1000 -
0+
0_
1!
0"
#12150000
1a
0X
0\
0Y
#12200000
0b
b0 #
b0 -
#12250000
1.
#12300000
1"
#13000000
14
1A
1N
b1111 %
b1111 '
#13050000
09
17
0F
1D
0S
1Q
#13100000
1;
1H
1U
b111 #
b111 -
#14000000
0A
0N
1<
b1001 %
b1001 '
b1010 $
b1010 &
#14050000
1F
0D
1S
0Q
0C
#14100000
1@
0H
0U
b1 #
b1 -
#14150000
1H
b11 #
b11 -
#15000000
04
1A
1/
b1010 %
b1010 '
b1011 $
b1011 &
#15050000
19
07
0F
1=
06
#15100000
13
0;
b10 #
b10 -
0@
1*
#15150000
1;
0H
b1 #
b1 -
0T
1R
#15200000
1U
b101 #
b101 -
